topsis/101903151.py
topsis_Akshit_101903151-1.0.0.dist-info/LICENSE
topsis_Akshit_101903151-1.0.0.dist-info/METADATA
topsis_Akshit_101903151-1.0.0.dist-info/WHEEL
topsis_Akshit_101903151-1.0.0.dist-info/top_level.txt
topsis_Akshit_101903151-1.0.0.dist-info/RECORD
