Metadata-Version: 2.1
Name: topsis-Akshit-101903151
Version: 1.0.0
Summary: Multiple criteria decision making (MCDM) using TOPSIS
Home-page: UNKNOWN
Author: Akshit
Author-email: akshitbeniwal26@gmail.com
License: MIT
Platform: UNKNOWN
Classifier: License :: OSI Approved :: MIT License
Classifier: Programming Language :: Python :: 3.6
Classifier: Programming Language :: Python :: 3.7
Classifier: Programming Language :: Python :: 3.8
Classifier: Programming Language :: Python :: 3.9
License-File: LICENSE
